csnp/__init__.py
csnp/plugin.py
csnp-0.0.8.dist-info/LICENSE
csnp-0.0.8.dist-info/METADATA
csnp-0.0.8.dist-info/WHEEL
csnp-0.0.8.dist-info/entry_points.txt
csnp-0.0.8.dist-info/top_level.txt
csnp-0.0.8.dist-info/RECORD
