Metadata-Version: 2.1
Name: csnp
Version: 0.0.8
Summary: crew member sentry notification plugin
Home-page: https://github.com/xiaomao361/csnp
Author: zhouwei
Author-email: xiaomao361@163.com
License: MIT
Keywords: crew sentry notification
Classifier: Framework :: Django
Classifier: Intended Audience :: Developers
Classifier: Intended Audience :: System Administrators
Classifier: Operating System :: OS Independent
Classifier: Topic :: Software Development
License-File: LICENSE
Requires-Dist: sentry (>10.0.1)
Requires-Dist: requests
